odoo8_addon_purchase_partial_invoicing-8.0.0.1.2-py2.7-nspkg.pth
odoo_addons/purchase_partial_invoicing/purchase.py
odoo_addons/purchase_partial_invoicing/purchase_view.xml
odoo_addons/purchase_partial_invoicing/__openerp__.py
odoo_addons/purchase_partial_invoicing/__init__.py
odoo_addons/purchase_partial_invoicing/README.rst
odoo_addons/purchase_partial_invoicing/i18n/zh_CN.po
odoo_addons/purchase_partial_invoicing/i18n/ru.po
odoo_addons/purchase_partial_invoicing/i18n/pt.po
odoo_addons/purchase_partial_invoicing/i18n/it.po
odoo_addons/purchase_partial_invoicing/i18n/es.po
odoo_addons/purchase_partial_invoicing/i18n/nl_BE.po
odoo_addons/purchase_partial_invoicing/i18n/ar.po
odoo_addons/purchase_partial_invoicing/i18n/lt.po
odoo_addons/purchase_partial_invoicing/i18n/ro.po
odoo_addons/purchase_partial_invoicing/i18n/tr.po
odoo_addons/purchase_partial_invoicing/i18n/hr.po
odoo_addons/purchase_partial_invoicing/i18n/bg.po
odoo_addons/purchase_partial_invoicing/i18n/es_EC.po
odoo_addons/purchase_partial_invoicing/i18n/gl.po
odoo_addons/purchase_partial_invoicing/i18n/ca.po
odoo_addons/purchase_partial_invoicing/i18n/es_CR.po
odoo_addons/purchase_partial_invoicing/i18n/sl.po
odoo_addons/purchase_partial_invoicing/i18n/th.po
odoo_addons/purchase_partial_invoicing/i18n/es_ES.po
odoo_addons/purchase_partial_invoicing/i18n/cs.po
odoo_addons/purchase_partial_invoicing/i18n/pt_PT.po
odoo_addons/purchase_partial_invoicing/i18n/purchase_partial_invoicing.pot
odoo_addons/purchase_partial_invoicing/i18n/et.po
odoo_addons/purchase_partial_invoicing/i18n/nl.po
odoo_addons/purchase_partial_invoicing/i18n/am.po
odoo_addons/purchase_partial_invoicing/i18n/de.po
odoo_addons/purchase_partial_invoicing/i18n/vi.po
odoo_addons/purchase_partial_invoicing/i18n/fr.po
odoo_addons/purchase_partial_invoicing/i18n/pl.po
odoo_addons/purchase_partial_invoicing/i18n/pt_BR.po
odoo_addons/purchase_partial_invoicing/i18n/el_GR.po
odoo8_addon_purchase_partial_invoicing-8.0.0.1.2.dist-info/top_level.txt
odoo8_addon_purchase_partial_invoicing-8.0.0.1.2.dist-info/WHEEL
odoo8_addon_purchase_partial_invoicing-8.0.0.1.2.dist-info/RECORD
odoo8_addon_purchase_partial_invoicing-8.0.0.1.2.dist-info/metadata.json
odoo8_addon_purchase_partial_invoicing-8.0.0.1.2.dist-info/DESCRIPTION.rst
odoo8_addon_purchase_partial_invoicing-8.0.0.1.2.dist-info/METADATA
odoo8_addon_purchase_partial_invoicing-8.0.0.1.2.dist-info/namespace_packages.txt
