Metadata-Version: 2.0
Name: odoo8-addon-purchase-partial-invoicing
Version: 8.0.0.1.2
Summary: Purchase partial invoicing
Home-page: http://www.agilebg.com
Author: UNKNOWN
Author-email: UNKNOWN
License: AGPL-3
Platform: UNKNOWN
Requires-Dist: odoo (<9.0a,>=8.0a)
Requires-Dist: odoo8-addon-base-suspend-security
Classifier: Programming Language :: Python :: 2.7
Classifier: Framework :: Odoo
Classifier: License :: OSI Approved :: GNU Affero General Public License v3
